utils_optima/__init__.py
utils_optima/libs.py
utils_optima/utilMethods.py
utils_optima/utilStrings.py
UtilsOptima-1.2.dist-info/LICENSE
UtilsOptima-1.2.dist-info/METADATA
UtilsOptima-1.2.dist-info/WHEEL
UtilsOptima-1.2.dist-info/top_level.txt
UtilsOptima-1.2.dist-info/RECORD
