Metadata-Version: 2.1
Name: UtilsOptima
Version: 1.2
Summary: Usado para los metodos y mensajes comunmente usados en nuestros proyectos.
Home-page: https://github.com/tecnoglass-optima/utils_optima
Author: Cesar Corbacho
Author-email: cesar.corbacho@tecnoglass.com
License: UNKNOWN
Download-URL: https://github.com/tecnoglass-optima/utils_optima/tarball/1.2
Platform: UNKNOWN
Classifier: Programming Language :: Python :: 3
Classifier: Operating System :: OS Independent
Requires-Python: >=3.6
License-File: LICENSE
